diffusesr_helper/__init__.py
diffusesr_helper/core.so
diffusesr_helper-0.1.0.dist-info/licenses/LICENSE
diffusesr_helper-0.1.0.dist-info/METADATA
diffusesr_helper-0.1.0.dist-info/WHEEL
diffusesr_helper-0.1.0.dist-info/top_level.txt
diffusesr_helper-0.1.0.dist-info/RECORD
